[{"idEntity":5950208,"label":"Egypt","extractorType":null,"nerdType":"http://nerd.eurecom.fr/ontology#Location","uri":"http://dbpedia.org/resource/Egypt","confidence":0.107299,"relevance":0.5,"extractor":"nerdml","startChar":45,"endChar":50},{"idEntity":5950209,"label":"mass protests","extractorType":null,"nerdType":"http://nerd.eurecom.fr/ontology#Thing","uri":"http://dbpedia.org/resource/2009%E2%80%9310_Iranian_election_protests","confidence":0.6523,"relevance":0.5,"extractor":"nerdml","startChar":71,"endChar":84},{"idEntity":5950210,"label":"president","extractorType":null,"nerdType":"http://nerd.eurecom.fr/ontology#Thing","uri":"http://dbpedia.org/resource/President_of_the_United_States","confidence":0.6565,"relevance":0.5,"extractor":"nerdml","startChar":144,"endChar":153},{"idEntity":5950211,"label":"Mohamed Morsi","extractorType":null,"nerdType":"http://nerd.eurecom.fr/ontology#Person","uri":"http://dbpedia.org/resource/Mohamed_Morsi","confidence":1.65403,"relevance":0.5,"extractor":"nerdml","startChar":155,"endChar":168},{"idEntity":5950212,"label":"political leaders","extractorType":null,"nerdType":"http://nerd.eurecom.fr/ontology#Thing","uri":"http://dbpedia.org/resource/Politician","confidence":0.0338247,"relevance":0.5,"extractor":"nerdml","startChar":173,"endChar":190},{"idEntity":5950213,"label":"civilian","extractorType":null,"nerdType":"http://nerd.eurecom.fr/ontology#Thing","uri":"http://dbpedia.org/resource/Civilian","confidence":0.0661179,"relevance":0.5,"extractor":"nerdml","startChar":224,"endChar":232},{"idEntity":5950214,"label":"Morsi","extractorType":null,"nerdType":"http://nerd.eurecom.fr/ontology#Person","uri":"http://dbpedia.org/resource/Mohamed_Morsi","confidence":0.6166,"relevance":0.5,"extractor":"nerdml","startChar":332,"endChar":337},{"idEntity":5950215,"label":"Cairo","extractorType":null,"nerdType":"http://nerd.eurecom.fr/ontology#Location","uri":"http://dbpedia.org/resource/Cairo","confidence":0.8194,"relevance":0.5,"extractor":"nerdml","startChar":369,"endChar":374},{"idEntity":5950216,"label":"massacre","extractorType":null,"nerdType":"http://nerd.eurecom.fr/ontology#Thing","uri":"http://dbpedia.org/resource/Massacre","confidence":0.0799649,"relevance":0.5,"extractor":"nerdml","startChar":427,"endChar":435},{"idEntity":5950217,"label":"Muslim Brotherhood","extractorType":null,"nerdType":"http://nerd.eurecom.fr/ontology#Organization","uri":"http://dbpedia.org/resource/Muslim_Brotherhood","confidence":1.73596,"relevance":0.5,"extractor":"nerdml","startChar":439,"endChar":457},{"idEntity":5950218,"label":"army","extractorType":null,"nerdType":"http://nerd.eurecom.fr/ontology#Organization","uri":"http://dbpedia.org/resource/French_Army","confidence":0.0460489,"relevance":0.5,"extractor":"nerdml","startChar":489,"endChar":493},{"idEntity":5950219,"label":"terrorist attack","extractorType":null,"nerdType":"http://nerd.eurecom.fr/ontology#Thing","uri":"http://dbpedia.org/resource/Terrorism","confidence":0.6959,"relevance":0.5,"extractor":"nerdml","startChar":513,"endChar":529},{"idEntity":5950220,"label":"authorities","extractorType":null,"nerdType":"http://nerd.eurecom.fr/ontology#Thing","uri":"http://dbpedia.org/resource/Authority","confidence":0.0136966,"relevance":0.5,"extractor":"nerdml","startChar":537,"endChar":548},{"idEntity":5950221,"label":"killed","extractorType":null,"nerdType":"http://nerd.eurecom.fr/ontology#Thing","uri":"http://dbpedia.org/resource/Death","confidence":0.6948,"relevance":0.5,"extractor":"nerdml","startChar":593,"endChar":599},{"idEntity":5950222,"label":"families","extractorType":null,"nerdType":"http://nerd.eurecom.fr/ontology#Thing","uri":"http://dbpedia.org/resource/Family","confidence":0.0164881,"relevance":0.5,"extractor":"nerdml","startChar":606,"endChar":614},{"idEntity":5950223,"label":"autopsy","extractorType":null,"nerdType":"http://nerd.eurecom.fr/ontology#Thing","uri":"http://dbpedia.org/resource/Autopsy","confidence":0.7771,"relevance":0.5,"extractor":"nerdml","startChar":631,"endChar":638},{"idEntity":5950224,"label":"reports","extractorType":null,"nerdType":"http://nerd.eurecom.fr/ontology#Thing","uri":"http://dbpedia.org/resource/Report","confidence":0.00239587,"relevance":0.5,"extractor":"nerdml","startChar":639,"endChar":646},{"idEntity":5950225,"label":"dispute","extractorType":null,"nerdType":"http://nerd.eurecom.fr/ontology#Thing","uri":"http://dbpedia.org/resource/Controversy","confidence":0.0177381,"relevance":0.5,"extractor":"nerdml","startChar":663,"endChar":670},{"idEntity":5950226,"label":"deaths","extractorType":null,"nerdType":"http://nerd.eurecom.fr/ontology#Thing","uri":"http://dbpedia.org/resource/Death","confidence":0.7163,"relevance":0.5,"extractor":"nerdml","startChar":704,"endChar":710},{"idEntity":5950227,"label":"Egyptian health ministry","extractorType":null,"nerdType":"http://nerd.eurecom.fr/ontology#Thing","uri":"http://dbpedia.org/resource/Ministry_of_Health_(Egypt)","confidence":0.8039,"relevance":0.5,"extractor":"nerdml","startChar":716,"endChar":740},{"idEntity":5950228,"label":"dead","extractorType":null,"nerdType":"http://nerd.eurecom.fr/ontology#Thing","uri":"http://dbpedia.org/resource/Death","confidence":0.6706,"relevance":0.5,"extractor":"nerdml","startChar":783,"endChar":787},{"idEntity":5950229,"label":"Muslim Brotherhood","extractorType":null,"nerdType":"http://nerd.eurecom.fr/ontology#Organization","uri":"http://dbpedia.org/resource/Muslim_Brotherhood","confidence":1.73596,"relevance":0.5,"extractor":"nerdml","startChar":795,"endChar":813},{"idEntity":5950230,"label":"UN secretary general","extractorType":null,"nerdType":"http://nerd.eurecom.fr/ontology#Thing","uri":"http://dbpedia.org/resource/Secretary-General_of_the_United_Nations","confidence":0.7941,"relevance":0.5,"extractor":"nerdml","startChar":825,"endChar":845},{"idEntity":5950231,"label":"Ban Ki-moon","extractorType":null,"nerdType":"http://nerd.eurecom.fr/ontology#Person","uri":"http://dbpedia.org/resource/Ban_Ki-moon","confidence":1.209,"relevance":0.5,"extractor":"nerdml","startChar":846,"endChar":857},{"idEntity":5950232,"label":"office","extractorType":null,"nerdType":"http://nerd.eurecom.fr/ontology#Thing","uri":"http://dbpedia.org/resource/Office","confidence":0.00731473,"relevance":0.5,"extractor":"nerdml","startChar":949,"endChar":955},{"idEntity":5950233,"label":"Secretary-General","extractorType":null,"nerdType":"http://nerd.eurecom.fr/ontology#Thing","uri":"http://dbpedia.org/resource/Secretary-General_of_the_United_Nations","confidence":0.6759,"relevance":0.5,"extractor":"nerdml","startChar":967,"endChar":984},{"idEntity":5950234,"label":"justice","extractorType":null,"nerdType":"http://nerd.eurecom.fr/ontology#Thing","uri":"http://dbpedia.org/resource/Justice","confidence":0.6221,"relevance":0.5,"extractor":"nerdml","startChar":1148,"endChar":1155},{"idEntity":5950235,"label":"Egyptian army","extractorType":null,"nerdType":"http://nerd.eurecom.fr/ontology#Thing","uri":"http://dbpedia.org/resource/Egyptian_Armed_Forces","confidence":0.7633,"relevance":0.5,"extractor":"nerdml","startChar":1163,"endChar":1176},{"idEntity":5950236,"label":"excessive force","extractorType":null,"nerdType":"http://nerd.eurecom.fr/ontology#Thing","uri":"http://dbpedia.org/resource/Police_brutality","confidence":0.6923,"relevance":0.5,"extractor":"nerdml","startChar":1201,"endChar":1216},{"idEntity":5950237,"label":"Morsi","extractorType":null,"nerdType":"http://nerd.eurecom.fr/ontology#Person","uri":"http://dbpedia.org/resource/Mohamed_Morsi","confidence":0.666,"relevance":0.5,"extractor":"nerdml","startChar":1229,"endChar":1234},{"idEntity":5950238,"label":"independent","extractorType":null,"nerdType":"http://nerd.eurecom.fr/ontology#Product","uri":"http://dbpedia.org/resource/The_Independent","confidence":0.661,"relevance":0.5,"extractor":"nerdml","startChar":1264,"endChar":1275},{"idEntity":5950239,"label":"massacre","extractorType":null,"nerdType":"http://nerd.eurecom.fr/ontology#Thing","uri":"http://dbpedia.org/resource/Massacre","confidence":0.0808074,"relevance":0.5,"extractor":"nerdml","startChar":1307,"endChar":1315},{"idEntity":5950240,"label":"AP","extractorType":null,"nerdType":"http://nerd.eurecom.fr/ontology#Thing","uri":"http://dbpedia.org/resource/Associated_Press","confidence":0.6324,"relevance":0.5,"extractor":"nerdml","startChar":1329,"endChar":1331},{"idEntity":5950241,"label":"spokesman","extractorType":null,"nerdType":"http://nerd.eurecom.fr/ontology#Thing","uri":"http://dbpedia.org/resource/Spokesperson","confidence":0.0142937,"relevance":0.5,"extractor":"nerdml","startChar":1333,"endChar":1342},{"idEntity":5950242,"label":"Colonel","extractorType":null,"nerdType":"http://nerd.eurecom.fr/ontology#Thing","uri":"http://dbpedia.org/resource/Colonel","confidence":0.6878,"relevance":0.5,"extractor":"nerdml","startChar":1343,"endChar":1350},{"idEntity":5950243,"label":"Ahmed Mohammed Ali","extractorType":null,"nerdType":"http://nerd.eurecom.fr/ontology#Thing","uri":"http://dbpedia.org/resource/Ahmed_Mohammed_Ali","confidence":0.7715,"relevance":0.5,"extractor":"nerdml","startChar":1351,"endChar":1369},{"idEntity":5950244,"label":"excessive force","extractorType":null,"nerdType":"http://nerd.eurecom.fr/ontology#Thing","uri":"http://dbpedia.org/resource/Police_brutality","confidence":0.6558,"relevance":0.5,"extractor":"nerdml","startChar":1382,"endChar":1397},{"idEntity":5950245,"label":"live ammunition","extractorType":null,"nerdType":"http://nerd.eurecom.fr/ontology#Product","uri":"http://dbpedia.org/resource/Ammunition","confidence":0.0234846,"relevance":0.5,"extractor":"nerdml","startChar":1447,"endChar":1462},{"idEntity":5950246,"label":"Amnesty","extractorType":null,"nerdType":"http://nerd.eurecom.fr/ontology#Organization","uri":"http://dbpedia.org/resource/Amnesty_International","confidence":0.6439,"relevance":0.5,"extractor":"nerdml","startChar":1511,"endChar":1518},{"idEntity":5950247,"label":"inquiry","extractorType":null,"nerdType":"http://nerd.eurecom.fr/ontology#Thing","uri":"http://dbpedia.org/resource/Inquiry","confidence":0.012519,"relevance":0.5,"extractor":"nerdml","startChar":1533,"endChar":1540},{"idEntity":5950248,"label":"white-washing","extractorType":null,"nerdType":"http://nerd.eurecom.fr/ontology#Thing","uri":"http://dbpedia.org/resource/Whitewash","confidence":0.653,"relevance":0.5,"extractor":"nerdml","startChar":1571,"endChar":1584},{"idEntity":5950249,"label":"abuses","extractorType":null,"nerdType":"http://nerd.eurecom.fr/ontology#Thing","uri":"http://dbpedia.org/resource/Abuse","confidence":0.0136118,"relevance":0.5,"extractor":"nerdml","startChar":1585,"endChar":1591},{"idEntity":5950250,"label":"Egyptian army","extractorType":null,"nerdType":"http://nerd.eurecom.fr/ontology#Thing","uri":"http://dbpedia.org/resource/Egyptian_Armed_Forces","confidence":0.7412,"relevance":0.5,"extractor":"nerdml","startChar":1599,"endChar":1612},{"idEntity":5950251,"label":"Samir Radwan","extractorType":null,"nerdType":"http://nerd.eurecom.fr/ontology#Person","uri":"http://dbpedia.org/resource/Samir_Radwan","confidence":0.8642,"relevance":0.5,"extractor":"nerdml","startChar":1616,"endChar":1628},{"idEntity":5950252,"label":"prime minister","extractorType":null,"nerdType":"http://nerd.eurecom.fr/ontology#Thing","uri":"http://dbpedia.org/resource/Prime_minister","confidence":0.7051,"relevance":0.5,"extractor":"nerdml","startChar":1650,"endChar":1664},{"idEntity":5950253,"label":"the Guardian","extractorType":null,"nerdType":"http://nerd.eurecom.fr/ontology#Product","uri":"http://dbpedia.org/resource/The_Guardian","confidence":0.7782,"relevance":0.5,"extractor":"nerdml","startChar":1671,"endChar":1683},{"idEntity":5950254,"label":"economy","extractorType":null,"nerdType":"http://nerd.eurecom.fr/ontology#Thing","uri":"http://dbpedia.org/resource/Economy","confidence":0.0195803,"relevance":0.5,"extractor":"nerdml","startChar":1741,"endChar":1748},{"idEntity":5950255,"label":"atmosphere","extractorType":null,"nerdType":"http://nerd.eurecom.fr/ontology#Thing","uri":"http://dbpedia.org/resource/Atmosphere_of_Earth","confidence":0.6273,"relevance":0.5,"extractor":"nerdml","startChar":1791,"endChar":1801},{"idEntity":5950256,"label":"polarisation","extractorType":null,"nerdType":"http://nerd.eurecom.fr/ontology#Thing","uri":"http://dbpedia.org/resource/Polarization_(waves)","confidence":0.10842,"relevance":0.5,"extractor":"nerdml","startChar":1813,"endChar":1825},{"idEntity":5950257,"label":"Radwan","extractorType":null,"nerdType":"http://nerd.eurecom.fr/ontology#Thing","uri":"http://dbpedia.org/resource/Fakhr_al-Mulk_Radwan","confidence":0.6985,"relevance":0.5,"extractor":"nerdml","startChar":1827,"endChar":1833},{"idEntity":5950258,"label":"economy","extractorType":null,"nerdType":"http://nerd.eurecom.fr/ontology#Thing","uri":"http://dbpedia.org/resource/Economy","confidence":0.0195803,"relevance":0.5,"extractor":"nerdml","startChar":1877,"endChar":1884},{"idEntity":5950259,"label":"Egyptian","extractorType":null,"nerdType":"http://nerd.eurecom.fr/ontology#Person","uri":"http://dbpedia.org/resource/Egyptians","confidence":0.668,"relevance":0.5,"extractor":"nerdml","startChar":1919,"endChar":1927},{"idEntity":5950260,"label":"society","extractorType":null,"nerdType":"http://nerd.eurecom.fr/ontology#Thing","uri":"http://dbpedia.org/resource/Society","confidence":0.0542305,"relevance":0.5,"extractor":"nerdml","startChar":1928,"endChar":1935},{"idEntity":5950261,"label":"Muslim Brotherhood","extractorType":null,"nerdType":"http://nerd.eurecom.fr/ontology#Organization","uri":"http://dbpedia.org/resource/Muslim_Brotherhood","confidence":1.47148,"relevance":0.5,"extractor":"nerdml","startChar":1958,"endChar":1976},{"idEntity":5950262,"label":"financial backing","extractorType":null,"nerdType":"http://nerd.eurecom.fr/ontology#Thing","uri":"http://dbpedia.org/resource/Financier","confidence":0.00824151,"relevance":0.5,"extractor":"nerdml","startChar":2021,"endChar":2038},{"idEntity":5950263,"label":"Gulf","extractorType":null,"nerdType":"http://nerd.eurecom.fr/ontology#Location","uri":"http://dbpedia.org/resource/Persian_Gulf","confidence":0.655,"relevance":0.5,"extractor":"nerdml","startChar":2048,"endChar":2052},{"idEntity":5950264,"label":"United Arab Emirates","extractorType":null,"nerdType":"http://nerd.eurecom.fr/ontology#Thing","uri":"http://dbpedia.org/resource/United_Arab_Emirates","confidence":1.63582,"relevance":0.5,"extractor":"nerdml","startChar":2058,"endChar":2078},{"idEntity":5950265,"label":"Egypt","extractorType":null,"nerdType":"http://nerd.eurecom.fr/ontology#Location","uri":"http://dbpedia.org/resource/Egypt","confidence":0.851,"relevance":0.5,"extractor":"nerdml","startChar":2099,"endChar":2104},{"idEntity":5950266,"label":"Reuters","extractorType":null,"nerdType":"http://nerd.eurecom.fr/ontology#Thing","uri":"http://dbpedia.org/resource/Reuters","confidence":0.8248,"relevance":0.5,"extractor":"nerdml","startChar":2149,"endChar":2156},{"idEntity":5950267,"label":"Saudi Arabia","extractorType":null,"nerdType":"http://nerd.eurecom.fr/ontology#Thing","uri":"http://dbpedia.org/resource/Saudi_Arabia","confidence":1.59466,"relevance":0.5,"extractor":"nerdml","startChar":2180,"endChar":2192},{"idEntity":5950268,"label":"Egypt","extractorType":null,"nerdType":"http://nerd.eurecom.fr/ontology#Location","uri":"http://dbpedia.org/resource/Egypt","confidence":0.8433,"relevance":0.5,"extractor":"nerdml","startChar":2202,"endChar":2207},{"idEntity":5950269,"label":"Tamarod","extractorType":null,"nerdType":"http://nerd.eurecom.fr/ontology#Thing","uri":"http://dbpedia.org/resource/Tamarod","confidence":0.8957,"relevance":0.5,"extractor":"nerdml","startChar":2234,"endChar":2241},{"idEntity":5950270,"label":"campaign","extractorType":null,"nerdType":"http://nerd.eurecom.fr/ontology#Event","uri":"http://dbpedia.org/resource/Hundred_Days","confidence":0.0283867,"relevance":0.5,"extractor":"nerdml","startChar":2242,"endChar":2250},{"idEntity":5950271,"label":"petition","extractorType":null,"nerdType":"http://nerd.eurecom.fr/ontology#Product","uri":"http://dbpedia.org/resource/Petition","confidence":0.0211537,"relevance":0.5,"extractor":"nerdml","startChar":2284,"endChar":2292},{"idEntity":5950272,"label":"Morsi","extractorType":null,"nerdType":"http://nerd.eurecom.fr/ontology#Person","uri":"http://dbpedia.org/resource/Mohamed_Morsi","confidence":0.6468,"relevance":0.5,"extractor":"nerdml","startChar":2305,"endChar":2310},{"idEntity":5950273,"label":"constitution","extractorType":null,"nerdType":"http://nerd.eurecom.fr/ontology#Thing","uri":"http://dbpedia.org/resource/Constitution","confidence":0.0568821,"relevance":0.5,"extractor":"nerdml","startChar":2367,"endChar":2379},{"idEntity":5950274,"label":"Egypt Independent","extractorType":null,"nerdType":"http://nerd.eurecom.fr/ontology#Thing","uri":"http://dbpedia.org/resource/Egypt_Independent","confidence":0.8486,"relevance":0.5,"extractor":"nerdml","startChar":2418,"endChar":2435},{"idEntity":5950275,"label":"campaign","extractorType":null,"nerdType":"http://nerd.eurecom.fr/ontology#Event","uri":"http://dbpedia.org/resource/Hundred_Days","confidence":0.0283867,"relevance":0.5,"extractor":"nerdml","startChar":2472,"endChar":2480},{"idEntity":5950276,"label":"charter","extractorType":null,"nerdType":"http://nerd.eurecom.fr/ontology#Thing","uri":"http://dbpedia.org/resource/Charter","confidence":0.0527084,"relevance":0.5,"extractor":"nerdml","startChar":2503,"endChar":2510},{"idEntity":5950277,"label":"Twitter","extractorType":null,"nerdType":"http://nerd.eurecom.fr/ontology#Product","uri":"http://dbpedia.org/resource/Twitter","confidence":0.8059,"relevance":0.5,"extractor":"nerdml","startChar":2633,"endChar":2640},{"idEntity":5950278,"label":"hat tip","extractorType":null,"nerdType":"http://nerd.eurecom.fr/ontology#Thing","uri":"http://dbpedia.org/resource/Hat_tip","confidence":0.8284,"relevance":0.5,"extractor":"nerdml","startChar":2649,"endChar":2656},{"idEntity":5950279,"label":"United Arab Emirates","extractorType":null,"nerdType":"http://nerd.eurecom.fr/ontology#Thing","uri":"http://dbpedia.org/resource/United_Arab_Emirates","confidence":1.63582,"relevance":0.5,"extractor":"nerdml","startChar":2682,"endChar":2702},{"idEntity":5950280,"label":"Egypt","extractorType":null,"nerdType":"http://nerd.eurecom.fr/ontology#Location","uri":"http://dbpedia.org/resource/Egypt","confidence":0.853,"relevance":0.5,"extractor":"nerdml","startChar":2723,"endChar":2728},{"idEntity":5950281,"label":"Reuters","extractorType":null,"nerdType":"http://nerd.eurecom.fr/ontology#Thing","uri":"http://dbpedia.org/resource/Reuters","confidence":0.8235,"relevance":0.5,"extractor":"nerdml","startChar":2773,"endChar":2780},{"idEntity":5950282,"label":"Egypt","extractorType":null,"nerdType":"http://nerd.eurecom.fr/ontology#Location","uri":"http://dbpedia.org/resource/Egypt","confidence":0.8473,"relevance":0.5,"extractor":"nerdml","startChar":2782,"endChar":2787},{"idEntity":5950283,"label":"Republican Guards","extractorType":null,"nerdType":"http://nerd.eurecom.fr/ontology#Organization","uri":"http://dbpedia.org/resource/Republican_Guard_(France)","confidence":0.0535916,"relevance":0.5,"extractor":"nerdml","startChar":2883,"endChar":2900},{"idEntity":5950284,"label":"headquarters","extractorType":null,"nerdType":"http://nerd.eurecom.fr/ontology#Thing","uri":"http://dbpedia.org/resource/Headquarters","confidence":0.0230971,"relevance":0.5,"extractor":"nerdml","startChar":2901,"endChar":2913},{"idEntity":5950285,"label":"Ahram","extractorType":null,"nerdType":"http://nerd.eurecom.fr/ontology#Product","uri":"http://dbpedia.org/resource/Al-Ahram","confidence":0.066765,"relevance":0.5,"extractor":"nerdml","startChar":2969,"endChar":2974},{"idEntity":5950286,"label":"reports","extractorType":null,"nerdType":"http://nerd.eurecom.fr/ontology#Thing","uri":"http://dbpedia.org/resource/Report","confidence":0.00239587,"relevance":0.5,"extractor":"nerdml","startChar":2975,"endChar":2982},{"idEntity":5950287,"label":"Cairo","extractorType":null,"nerdType":"http://nerd.eurecom.fr/ontology#Location","uri":"http://dbpedia.org/resource/Cairo","confidence":0.81,"relevance":0.5,"extractor":"nerdml","startChar":2987,"endChar":2992},{"idEntity":5950288,"label":"morgue","extractorType":null,"nerdType":"http://nerd.eurecom.fr/ontology#Thing","uri":"http://dbpedia.org/resource/Morgue","confidence":0.6475,"relevance":0.5,"extractor":"nerdml","startChar":3003,"endChar":3009},{"idEntity":5950289,"label":"massacre","extractorType":null,"nerdType":"http://nerd.eurecom.fr/ontology#Thing","uri":"http://dbpedia.org/resource/Massacre","confidence":0.0536958,"relevance":0.5,"extractor":"nerdml","startChar":3048,"endChar":3056},{"idEntity":5950290,"label":"friends","extractorType":null,"nerdType":"http://nerd.eurecom.fr/ontology#Thing","uri":"http://dbpedia.org/resource/Religious_Society_of_Friends","confidence":0.0112558,"relevance":0.5,"extractor":"nerdml","startChar":3086,"endChar":3093},{"idEntity":5950291,"label":"horror","extractorType":null,"nerdType":"http://nerd.eurecom.fr/ontology#Thing","uri":"http://dbpedia.org/resource/Horror_film","confidence":0.0157584,"relevance":0.5,"extractor":"nerdml","startChar":3155,"endChar":3161},{"idEntity":5950292,"label":"Mohamed","extractorType":null,"nerdType":"http://nerd.eurecom.fr/ontology#Thing","uri":"http://dbpedia.org/resource/Muhammad","confidence":0.6496,"relevance":0.5,"extractor":"nerdml","startChar":3202,"endChar":3209},{"idEntity":5950293,"label":"Abu","extractorType":null,"nerdType":"http://nerd.eurecom.fr/ontology#Thing","uri":"http://dbpedia.org/resource/Abuse","confidence":0.0136118,"relevance":0.5,"extractor":"nerdml","startChar":3210,"endChar":3213},{"idEntity":5950294,"label":"lecturer","extractorType":null,"nerdType":"http://nerd.eurecom.fr/ontology#Thing","uri":"http://dbpedia.org/resource/Lecturer","confidence":0.010491,"relevance":0.5,"extractor":"nerdml","startChar":3223,"endChar":3231},{"idEntity":5950295,"label":"al-Azhar university","extractorType":null,"nerdType":"http://nerd.eurecom.fr/ontology#Organization","uri":"http://dbpedia.org/resource/Al-Azhar_University","confidence":1.22659,"relevance":0.5,"extractor":"nerdml","startChar":3235,"endChar":3254},{"idEntity":5950296,"label":"friend","extractorType":null,"nerdType":"http://nerd.eurecom.fr/ontology#Thing","uri":"http://dbpedia.org/resource/Friendship","confidence":0.00685825,"relevance":0.5,"extractor":"nerdml","startChar":3292,"endChar":3298},{"idEntity":5950297,"label":"Mohamed Abdel Rahman","extractorType":null,"nerdType":"http://nerd.eurecom.fr/ontology#Person","uri":"http://dbpedia.org/resource/Mohamed_Abdel_Rahman","confidence":0.8609,"relevance":0.5,"extractor":"nerdml","startChar":3299,"endChar":3319},{"idEntity":5950298,"label":"chemist","extractorType":null,"nerdType":"http://nerd.eurecom.fr/ontology#Thing","uri":"http://dbpedia.org/resource/Chemistry","confidence":0.706,"relevance":0.5,"extractor":"nerdml","startChar":3323,"endChar":3330},{"idEntity":5950299,"label":"history of Egypt","extractorType":null,"nerdType":"http://nerd.eurecom.fr/ontology#Thing","uri":"http://dbpedia.org/resource/History_of_Egypt","confidence":0.7529,"relevance":0.5,"extractor":"nerdml","startChar":3358,"endChar":3374},{"idEntity":5950300,"label":"army","extractorType":null,"nerdType":"http://nerd.eurecom.fr/ontology#Organization","uri":"http://dbpedia.org/resource/French_Army","confidence":0.0460489,"relevance":0.5,"extractor":"nerdml","startChar":3377,"endChar":3381},{"idEntity":5950301,"label":"Abu","extractorType":null,"nerdType":"http://nerd.eurecom.fr/ontology#Thing","uri":"http://dbpedia.org/resource/Abuse","confidence":0.0136118,"relevance":0.5,"extractor":"nerdml","startChar":3383,"endChar":3386},{"idEntity":5950302,"label":"Islamists","extractorType":null,"nerdType":"http://nerd.eurecom.fr/ontology#Thing","uri":"http://dbpedia.org/resource/Islamism","confidence":0.7648,"relevance":0.5,"extractor":"nerdml","startChar":3404,"endChar":3413},{"idEntity":5950303,"label":"UN's","extractorType":null,"nerdType":"http://nerd.eurecom.fr/ontology#Location","uri":"http://dbpedia.org/resource/United_Nations","confidence":0.677,"relevance":0.5,"extractor":"nerdml","startChar":3469,"endChar":3473},{"idEntity":5950304,"label":"secretary general","extractorType":null,"nerdType":"http://nerd.eurecom.fr/ontology#Thing","uri":"http://dbpedia.org/resource/Secretary-General_of_the_United_Nations","confidence":0.7394,"relevance":0.5,"extractor":"nerdml","startChar":3474,"endChar":3491},{"idEntity":5950305,"label":"Ban Ki-moon","extractorType":null,"nerdType":"http://nerd.eurecom.fr/ontology#Person","uri":"http://dbpedia.org/resource/Ban_Ki-moon","confidence":1.08206,"relevance":0.5,"extractor":"nerdml","startChar":3493,"endChar":3504},{"idEntity":5950306,"label":"Morsi","extractorType":null,"nerdType":"http://nerd.eurecom.fr/ontology#Person","uri":"http://dbpedia.org/resource/Mohamed_Morsi","confidence":0.6331,"relevance":0.5,"extractor":"nerdml","startChar":3583,"endChar":3588},{"idEntity":5950307,"label":"office","extractorType":null,"nerdType":"http://nerd.eurecom.fr/ontology#Thing","uri":"http://dbpedia.org/resource/Office","confidence":0.00731473,"relevance":0.5,"extractor":"nerdml","startChar":3639,"endChar":3645},{"idEntity":5950308,"label":"Secretary-General","extractorType":null,"nerdType":"http://nerd.eurecom.fr/ontology#Thing","uri":"http://dbpedia.org/resource/Secretary-General_of_the_United_Nations","confidence":0.6527,"relevance":0.5,"extractor":"nerdml","startChar":3657,"endChar":3674},{"idEntity":5950309,"label":"justice","extractorType":null,"nerdType":"http://nerd.eurecom.fr/ontology#Thing","uri":"http://dbpedia.org/resource/Justice","confidence":0.6764,"relevance":0.5,"extractor":"nerdml","startChar":3838,"endChar":3845},{"idEntity":5950310,"label":"Ban","extractorType":null,"nerdType":"http://nerd.eurecom.fr/ontology#Person","uri":"http://dbpedia.org/resource/Ban_Ki-moon","confidence":0.0496355,"relevance":0.5,"extractor":"nerdml","startChar":3847,"endChar":3850},{"idEntity":5950311,"label":"office","extractorType":null,"nerdType":"http://nerd.eurecom.fr/ontology#Thing","uri":"http://dbpedia.org/resource/Office","confidence":0.00731473,"relevance":0.5,"extractor":"nerdml","startChar":3853,"endChar":3859},{"idEntity":5950312,"label":"Egypt","extractorType":null,"nerdType":"http://nerd.eurecom.fr/ontology#Location","uri":"http://dbpedia.org/resource/Ancient_Egypt","confidence":0.8371,"relevance":0.5,"extractor":"nerdml","startChar":3903,"endChar":3908},{"idEntity":5950313,"label":"consensus","extractorType":null,"nerdType":"http://nerd.eurecom.fr/ontology#Thing","uri":"http://dbpedia.org/resource/Consensus_decision-making","confidence":0.6519,"relevance":0.5,"extractor":"nerdml","startChar":3941,"endChar":3950},{"idEntity":5950314,"label":"Muslim Brotherhood","extractorType":null,"nerdType":"http://nerd.eurecom.fr/ontology#Organization","uri":"http://dbpedia.org/resource/Muslim_Brotherhood","confidence":1.48094,"relevance":0.5,"extractor":"nerdml","startChar":4006,"endChar":4024},{"idEntity":5950315,"label":"anger","extractorType":null,"nerdType":"http://nerd.eurecom.fr/ontology#Thing","uri":"http://dbpedia.org/resource/Anger","confidence":0.00697256,"relevance":0.5,"extractor":"nerdml","startChar":4055,"endChar":4060},{"idEntity":5950316,"label":"international community","extractorType":null,"nerdType":"http://nerd.eurecom.fr/ontology#Thing","uri":"http://dbpedia.org/resource/International_community","confidence":0.6222,"relevance":0.5,"extractor":"nerdml","startChar":4090,"endChar":4113},{"idEntity":5950317,"label":"Guardian","extractorType":null,"nerdType":"http://nerd.eurecom.fr/ontology#Product","uri":"http://dbpedia.org/resource/The_Guardian","confidence":0.7912,"relevance":0.5,"extractor":"nerdml","startChar":4134,"endChar":4142},{"idEntity":5950318,"label":"minister","extractorType":null,"nerdType":"http://nerd.eurecom.fr/ontology#Thing","uri":"http://dbpedia.org/resource/Minister_%28government%29","confidence":0.0303635,"relevance":0.5,"extractor":"nerdml","startChar":4151,"endChar":4159},{"idEntity":5950319,"label":"coup","extractorType":null,"nerdType":"http://nerd.eurecom.fr/ontology#Thing","uri":"http://dbpedia.org/resource/Coup_d'%C3%A9tat","confidence":0.6339,"relevance":0.5,"extractor":"nerdml","startChar":4206,"endChar":4210},{"idEntity":5950320,"label":"concern","extractorType":null,"nerdType":"http://nerd.eurecom.fr/ontology#Organization","uri":"http://dbpedia.org/resource/Concern_Worldwide","confidence":0.00187019,"relevance":0.5,"extractor":"nerdml","startChar":4285,"endChar":4292},{"idEntity":5950321,"label":"Muslim Brotherhood","extractorType":null,"nerdType":"http://nerd.eurecom.fr/ontology#Organization","uri":"http://dbpedia.org/resource/Muslim_Brotherhood","confidence":1.04926,"relevance":0.5,"extractor":"nerdml","startChar":4338,"endChar":4356},{"idEntity":5950322,"label":"financial backing","extractorType":null,"nerdType":"http://nerd.eurecom.fr/ontology#Thing","uri":"http://dbpedia.org/resource/Financier","confidence":0.00824151,"relevance":0.5,"extractor":"nerdml","startChar":4396,"endChar":4413},{"idEntity":5950323,"label":"Gulf","extractorType":null,"nerdType":"http://nerd.eurecom.fr/ontology#Event","uri":"http://dbpedia.org/resource/Gulf_War","confidence":0.048455,"relevance":0.5,"extractor":"nerdml","startChar":4423,"endChar":4427},{"idEntity":5950324,"label":"Bloomberg","extractorType":null,"nerdType":"http://nerd.eurecom.fr/ontology#Thing","uri":"http://dbpedia.org/resource/Bloomberg_L.P.","confidence":0.7148,"relevance":0.5,"extractor":"nerdml","startChar":4429,"endChar":4438},{"idEntity":5950325,"label":"reports","extractorType":null,"nerdType":"http://nerd.eurecom.fr/ontology#Thing","uri":"http://dbpedia.org/resource/Report","confidence":0.00239587,"relevance":0.5,"extractor":"nerdml","startChar":4439,"endChar":4446},{"idEntity":5950326,"label":"London","extractorType":null,"nerdType":"http://nerd.eurecom.fr/ontology#Location","uri":"http://dbpedia.org/resource/London","confidence":0.7147,"relevance":0.5,"extractor":"nerdml","startChar":4465,"endChar":4471},{"idEntity":5950327,"label":"Noah","extractorType":null,"nerdType":"http://nerd.eurecom.fr/ontology#Person","uri":"http://dbpedia.org/resource/Noah","confidence":0.6273,"relevance":0.5,"extractor":"nerdml","startChar":4492,"endChar":4496},{"idEntity":5950328,"label":"Capital Markets","extractorType":null,"nerdType":"http://nerd.eurecom.fr/ontology#Thing","uri":"http://dbpedia.org/resource/Capital_market","confidence":0.6839,"relevance":0.5,"extractor":"nerdml","startChar":4497,"endChar":4512},{"idEntity":5950329,"label":"EMEA","extractorType":null,"nerdType":"http://nerd.eurecom.fr/ontology#Thing","uri":"http://dbpedia.org/resource/Europe,_the_Middle_East_and_Africa","confidence":0.6807,"relevance":0.5,"extractor":"nerdml","startChar":4513,"endChar":4517},{"idEntity":5950330,"label":"agency","extractorType":null,"nerdType":"http://nerd.eurecom.fr/ontology#Organization","uri":"http://dbpedia.org/resource/Central_Intelligence_Agency","confidence":0.0420998,"relevance":0.5,"extractor":"nerdml","startChar":4532,"endChar":4538},{"idEntity":5950331,"label":"investment","extractorType":null,"nerdType":"http://nerd.eurecom.fr/ontology#Thing","uri":"http://dbpedia.org/resource/Investment","confidence":0.0139578,"relevance":0.5,"extractor":"nerdml","startChar":4578,"endChar":4588},{"idEntity":5950332,"label":"Saudi Arabia","extractorType":null,"nerdType":"http://nerd.eurecom.fr/ontology#Thing","uri":"http://dbpedia.org/resource/Saudi_Arabia","confidence":1.53911,"relevance":0.5,"extractor":"nerdml","startChar":4594,"endChar":4606},{"idEntity":5950333,"label":"UAE","extractorType":null,"nerdType":"http://nerd.eurecom.fr/ontology#Location","uri":"http://dbpedia.org/resource/United_Arab_Emirates","confidence":0.7911,"relevance":0.5,"extractor":"nerdml","startChar":4615,"endChar":4618},{"idEntity":5950334,"label":"Muslim Brotherhood","extractorType":null,"nerdType":"http://nerd.eurecom.fr/ontology#Organization","uri":"http://dbpedia.org/resource/Muslim_Brotherhood","confidence":1.04926,"relevance":0.5,"extractor":"nerdml","startChar":4653,"endChar":4671},{"idEntity":5950335,"label":"Middle East","extractorType":null,"nerdType":"http://nerd.eurecom.fr/ontology#Thing","uri":"http://dbpedia.org/resource/Middle_East","confidence":0.801,"relevance":0.5,"extractor":"nerdml","startChar":4705,"endChar":4716},{"idEntity":5950336,"label":"Africa","extractorType":null,"nerdType":"http://nerd.eurecom.fr/ontology#Location","uri":"http://dbpedia.org/resource/Africa","confidence":0.7129,"relevance":0.5,"extractor":"nerdml","startChar":4721,"endChar":4727},{"idEntity":5950337,"label":"economist","extractorType":null,"nerdType":"http://nerd.eurecom.fr/ontology#Product","uri":"http://dbpedia.org/resource/The_Economist","confidence":0.7842,"relevance":0.5,"extractor":"nerdml","startChar":4728,"endChar":4737},{"idEntity":5950338,"label":"VTB Capital","extractorType":null,"nerdType":"http://nerd.eurecom.fr/ontology#Thing","uri":"http://dbpedia.org/resource/VTB_Capital","confidence":0.8082,"relevance":0.5,"extractor":"nerdml","startChar":4741,"endChar":4752},{"idEntity":5950339,"label":"London","extractorType":null,"nerdType":"http://nerd.eurecom.fr/ontology#Location","uri":"http://dbpedia.org/resource/London","confidence":0.74,"relevance":0.5,"extractor":"nerdml","startChar":4760,"endChar":4766},{"idEntity":5950340,"label":"Aid","extractorType":null,"nerdType":"http://nerd.eurecom.fr/ontology#Thing","uri":"http://dbpedia.org/resource/AIDS","confidence":0.0285782,"relevance":0.5,"extractor":"nerdml","startChar":4774,"endChar":4777},{"idEntity":5950341,"label":"Saudi Arabia","extractorType":null,"nerdType":"http://nerd.eurecom.fr/ontology#Thing","uri":"http://dbpedia.org/resource/Saudi_Arabia","confidence":1.53911,"relevance":0.5,"extractor":"nerdml","startChar":4783,"endChar":4795},{"idEntity":5950342,"label":"UAE","extractorType":null,"nerdType":"http://nerd.eurecom.fr/ontology#Location","uri":"http://dbpedia.org/resource/United_Arab_Emirates","confidence":0.7889,"relevance":0.5,"extractor":"nerdml","startChar":4804,"endChar":4807},{"idEntity":5950343,"label":"balance of payments","extractorType":null,"nerdType":"http://nerd.eurecom.fr/ontology#Thing","uri":"http://dbpedia.org/resource/Balance_of_payments","confidence":0.7927,"relevance":0.5,"extractor":"nerdml","startChar":4825,"endChar":4844},{"idEntity":5950344,"label":"boost","extractorType":null,"nerdType":"http://nerd.eurecom.fr/ontology#Product","uri":"http://dbpedia.org/resource/Boost_C%2B%2B_Libraries","confidence":0.00182694,"relevance":0.5,"extractor":"nerdml","startChar":4859,"endChar":4864},{"idEntity":5950345,"label":"United Arab Emirates","extractorType":null,"nerdType":"http://nerd.eurecom.fr/ontology#Thing","uri":"http://dbpedia.org/resource/United_Arab_Emirates","confidence":1.60482,"relevance":0.5,"extractor":"nerdml","startChar":4922,"endChar":4942},{"idEntity":5950346,"label":"Egypt","extractorType":null,"nerdType":"http://nerd.eurecom.fr/ontology#Location","uri":"http://dbpedia.org/resource/Egypt","confidence":0.8403,"relevance":0.5,"extractor":"nerdml","startChar":4963,"endChar":4968},{"idEntity":5950347,"label":"this week","extractorType":null,"nerdType":"http://nerd.eurecom.fr/ontology#Organization","uri":"http://dbpedia.org/resource/BBC_News","confidence":0.0241556,"relevance":0.5,"extractor":"nerdml","startChar":4975,"endChar":4984},{"idEntity":5950348,"label":"Reuters","extractorType":null,"nerdType":"http://nerd.eurecom.fr/ontology#Thing","uri":"http://dbpedia.org/resource/Reuters","confidence":0.8211,"relevance":0.5,"extractor":"nerdml","startChar":4986,"endChar":4993},{"idEntity":5950349,"label":"reports","extractorType":null,"nerdType":"http://nerd.eurecom.fr/ontology#Thing","uri":"http://dbpedia.org/resource/Report","confidence":0.00239587,"relevance":0.5,"extractor":"nerdml","startChar":4994,"endChar":5001},{"idEntity":5950350,"label":"UAE government","extractorType":null,"nerdType":"http://nerd.eurecom.fr/ontology#Thing","uri":"http://dbpedia.org/resource/Politics_of_the_United_Arab_Emirates","confidence":0.624,"relevance":0.5,"extractor":"nerdml","startChar":5011,"endChar":5025},{"idEntity":5950351,"label":"source","extractorType":null,"nerdType":"http://nerd.eurecom.fr/ontology#Thing","uri":"http://dbpedia.org/resource/Source_code","confidence":0.0054408,"relevance":0.5,"extractor":"nerdml","startChar":5026,"endChar":5032},{"idEntity":5950352,"label":"Egypt","extractorType":null,"nerdType":"http://nerd.eurecom.fr/ontology#Location","uri":"http://dbpedia.org/resource/Egypt","confidence":0.8387,"relevance":0.5,"extractor":"nerdml","startChar":5058,"endChar":5063},{"idEntity":5950353,"label":"prime minister","extractorType":null,"nerdType":"http://nerd.eurecom.fr/ontology#Thing","uri":"http://dbpedia.org/resource/Prime_minister","confidence":0.6924,"relevance":0.5,"extractor":"nerdml","startChar":5071,"endChar":5085},{"idEntity":5950354,"label":"Switzerland","extractorType":null,"nerdType":"http://nerd.eurecom.fr/ontology#Location","uri":"http://dbpedia.org/resource/Switzerland","confidence":0.7975,"relevance":0.5,"extractor":"nerdml","startChar":5113,"endChar":5124},{"idEntity":5950355,"label":"country","extractorType":null,"nerdType":"http://nerd.eurecom.fr/ontology#Thing","uri":"http://dbpedia.org/resource/Country","confidence":0.00960617,"relevance":0.5,"extractor":"nerdml","startChar":5160,"endChar":5167},{"idEntity":5950356,"label":"Patrick Kingsley","extractorType":null,"nerdType":"http://nerd.eurecom.fr/ontology#Thing","uri":"http://dbpedia.org/resource/Patrick_Kingsley","confidence":0.8609,"relevance":0.5,"extractor":"nerdml","startChar":5169,"endChar":5185},{"idEntity":5950357,"label":"reports","extractorType":null,"nerdType":"http://nerd.eurecom.fr/ontology#Thing","uri":"http://dbpedia.org/resource/Report","confidence":0.00239587,"relevance":0.5,"extractor":"nerdml","startChar":5186,"endChar":5193},{"idEntity":5950358,"label":"Samir Radwan","extractorType":null,"nerdType":"http://nerd.eurecom.fr/ontology#Person","uri":"http://dbpedia.org/resource/Samir_Radwan","confidence":0.8708,"relevance":0.5,"extractor":"nerdml","startChar":5211,"endChar":5223},{"idEntity":5950359,"label":"audio","extractorType":null,"nerdType":"http://nerd.eurecom.fr/ontology#Thing","uri":"http://dbpedia.org/resource/Windows_Media_Audio","confidence":0.00134929,"relevance":0.5,"extractor":"nerdml","startChar":5231,"endChar":5236},{"idEntity":5950360,"label":"Cairo","extractorType":null,"nerdType":"http://nerd.eurecom.fr/ontology#Location","uri":"http://dbpedia.org/resource/Cairo","confidence":0.8081,"relevance":0.5,"extractor":"nerdml","startChar":5249,"endChar":5254},{"idEntity":5950361,"label":"Patrick","extractorType":null,"nerdType":"http://nerd.eurecom.fr/ontology#Thing","uri":"http://dbpedia.org/resource/Saint_Patrick","confidence":0.0105301,"relevance":0.5,"extractor":"nerdml","startChar":5256,"endChar":5263},{"idEntity":5950362,"label":"Patrick","extractorType":null,"nerdType":"http://nerd.eurecom.fr/ontology#Thing","uri":"http://dbpedia.org/resource/Saint_Patrick","confidence":0.0105301,"relevance":0.5,"extractor":"nerdml","startChar":5282,"endChar":5289},{"idEntity":5950363,"label":"appointment","extractorType":null,"nerdType":"http://nerd.eurecom.fr/ontology#Thing","uri":"http://dbpedia.org/resource/Appointment_of_Catholic_bishops","confidence":3.54342E-4,"relevance":0.5,"extractor":"nerdml","startChar":5299,"endChar":5310},{"idEntity":5950364,"label":"post","extractorType":null,"nerdType":"http://nerd.eurecom.fr/ontology#Product","uri":"http://dbpedia.org/resource/The_Jerusalem_Post","confidence":0.0244684,"relevance":0.5,"extractor":"nerdml","startChar":5376,"endChar":5380},{"idEntity":5950365,"label":"country","extractorType":null,"nerdType":"http://nerd.eurecom.fr/ontology#Thing","uri":"http://dbpedia.org/resource/Country","confidence":0.00960617,"relevance":0.5,"extractor":"nerdml","startChar":5515,"endChar":5522},{"idEntity":5950366,"label":"Patrick","extractorType":null,"nerdType":"http://nerd.eurecom.fr/ontology#Thing","uri":"http://dbpedia.org/resource/Saint_Patrick","confidence":0.0105301,"relevance":0.5,"extractor":"nerdml","startChar":5524,"endChar":5531},{"idEntity":5950367,"label":"Radwan","extractorType":null,"nerdType":"http://nerd.eurecom.fr/ontology#Thing","uri":"http://dbpedia.org/resource/Fakhr_al-Mulk_Radwan","confidence":0.6985,"relevance":0.5,"extractor":"nerdml","startChar":5538,"endChar":5544},{"idEntity":5950368,"label":"finance minister","extractorType":null,"nerdType":"http://nerd.eurecom.fr/ontology#Thing","uri":"http://dbpedia.org/resource/Finance_minister","confidence":0.0255619,"relevance":0.5,"extractor":"nerdml","startChar":5554,"endChar":5570},{"idEntity":5950369,"label":"Mubarak","extractorType":null,"nerdType":"http://nerd.eurecom.fr/ontology#Person","uri":"http://dbpedia.org/resource/Hosni_Mubarak","confidence":0.6579,"relevance":0.5,"extractor":"nerdml","startChar":5609,"endChar":5616},{"idEntity":5950370,"label":"development economist","extractorType":null,"nerdType":"http://nerd.eurecom.fr/ontology#Thing","uri":"http://dbpedia.org/resource/Development_economics","confidence":0.7297,"relevance":0.5,"extractor":"nerdml","startChar":5623,"endChar":5644},{"idEntity":5950371,"label":"Oman","extractorType":null,"nerdType":"http://nerd.eurecom.fr/ontology#Location","uri":"http://dbpedia.org/resource/Oman","confidence":0.8373,"relevance":0.5,"extractor":"nerdml","startChar":5685,"endChar":5689},{"idEntity":5950372,"label":"economic strategy","extractorType":null,"nerdType":"http://nerd.eurecom.fr/ontology#Thing","uri":"http://dbpedia.org/resource/Economics","confidence":0.0215708,"relevance":0.5,"extractor":"nerdml","startChar":5693,"endChar":5710},{"idEntity":5950373,"label":"Patrick","extractorType":null,"nerdType":"http://nerd.eurecom.fr/ontology#Thing","uri":"http://dbpedia.org/resource/Saint_Patrick","confidence":0.0105301,"relevance":0.5,"extractor":"nerdml","startChar":5712,"endChar":5719},{"idEntity":5950374,"label":"deal","extractorType":null,"nerdType":"http://nerd.eurecom.fr/ontology#Location","uri":"http://dbpedia.org/resource/Deal,_Kent","confidence":0.00359722,"relevance":0.5,"extractor":"nerdml","startChar":5805,"endChar":5809},{"idEntity":5950375,"label":"national reconciliation","extractorType":null,"nerdType":"http://nerd.eurecom.fr/ontology#Thing","uri":"http://dbpedia.org/resource/National_Reconciliation","confidence":0.0744526,"relevance":0.5,"extractor":"nerdml","startChar":5837,"endChar":5860},{"idEntity":5950376,"label":"Egypt","extractorType":null,"nerdType":"http://nerd.eurecom.fr/ontology#Location","uri":"http://dbpedia.org/resource/Egypt","confidence":0.8292,"relevance":0.5,"extractor":"nerdml","startChar":5871,"endChar":5876},{"idEntity":5950377,"label":"South African","extractorType":null,"nerdType":"http://nerd.eurecom.fr/ontology#Thing","uri":"http://dbpedia.org/resource/South_Africa","confidence":0.185432,"relevance":0.5,"extractor":"nerdml","startChar":5884,"endChar":5897},{"idEntity":5950378,"label":"national reconciliation","extractorType":null,"nerdType":"http://nerd.eurecom.fr/ontology#Thing","uri":"http://dbpedia.org/resource/National_Reconciliation","confidence":0.0744526,"relevance":0.5,"extractor":"nerdml","startChar":5921,"endChar":5944},{"idEntity":5950379,"label":"priority","extractorType":null,"nerdType":"http://nerd.eurecom.fr/ontology#Thing","uri":"http://dbpedia.org/resource/Priority_Records","confidence":0.00140206,"relevance":0.5,"extractor":"nerdml","startChar":5970,"endChar":5978},{"idEntity":5950380,"label":"economy","extractorType":null,"nerdType":"http://nerd.eurecom.fr/ontology#Thing","uri":"http://dbpedia.org/resource/Economy","confidence":0.0195803,"relevance":0.5,"extractor":"nerdml","startChar":5992,"endChar":5999},{"idEntity":5950381,"label":"choice","extractorType":null,"nerdType":"http://nerd.eurecom.fr/ontology#Person","uri":"http://dbpedia.org/resource/Pink_%28singer%29","confidence":0.00549137,"relevance":0.5,"extractor":"nerdml","startChar":6052,"endChar":6058},{"idEntity":5950382,"label":"economy","extractorType":null,"nerdType":"http://nerd.eurecom.fr/ontology#Thing","uri":"http://dbpedia.org/resource/Economy","confidence":0.0488358,"relevance":0.5,"extractor":"nerdml","startChar":6083,"endChar":6090},{"idEntity":5950383,"label":"Egypt","extractorType":null,"nerdType":"http://nerd.eurecom.fr/ontology#Location","uri":"http://dbpedia.org/resource/Egypt","confidence":0.835,"relevance":0.5,"extractor":"nerdml","startChar":6094,"endChar":6099},{"idEntity":5950384,"label":"century","extractorType":null,"nerdType":"http://nerd.eurecom.fr/ontology#Thing","uri":"http://dbpedia.org/resource/Century","confidence":0.016364,"relevance":0.5,"extractor":"nerdml","startChar":6157,"endChar":6164},{"idEntity":5950385,"label":"Radwan","extractorType":null,"nerdType":"http://nerd.eurecom.fr/ontology#Thing","uri":"http://dbpedia.org/resource/Fakhr_al-Mulk_Radwan","confidence":0.7154,"relevance":0.5,"extractor":"nerdml","startChar":6166,"endChar":6172},{"idEntity":5950386,"label":"Mohamed","extractorType":null,"nerdType":"http://nerd.eurecom.fr/ontology#Thing","uri":"http://dbpedia.org/resource/Muhammad","confidence":0.6754,"relevance":0.5,"extractor":"nerdml","startChar":6204,"endChar":6211},{"idEntity":5950387,"label":"vetoed","extractorType":null,"nerdType":"http://nerd.eurecom.fr/ontology#Thing","uri":"http://dbpedia.org/resource/Veto","confidence":0.0986126,"relevance":0.5,"extractor":"nerdml","startChar":6231,"endChar":6237},{"idEntity":5950388,"label":"Salafists","extractorType":null,"nerdType":"http://nerd.eurecom.fr/ontology#Thing","uri":"http://dbpedia.org/resource/Salafi_movement","confidence":0.7353,"relevance":0.5,"extractor":"nerdml","startChar":6245,"endChar":6254},{"idEntity":5950389,"label":"prime minister","extractorType":null,"nerdType":"http://nerd.eurecom.fr/ontology#Thing","uri":"http://dbpedia.org/resource/Prime_Minister_of_Pakistan","confidence":0.6945,"relevance":0.5,"extractor":"nerdml","startChar":6266,"endChar":6280},{"idEntity":5950390,"label":"Patrick","extractorType":null,"nerdType":"http://nerd.eurecom.fr/ontology#Thing","uri":"http://dbpedia.org/resource/Saint_Patrick","confidence":0.0105301,"relevance":0.5,"extractor":"nerdml","startChar":6282,"endChar":6289},{"idEntity":5950391,"label":"Salafist","extractorType":null,"nerdType":"http://nerd.eurecom.fr/ontology#Thing","uri":"http://dbpedia.org/resource/Salafi_movement","confidence":0.7959,"relevance":0.5,"extractor":"nerdml","startChar":6300,"endChar":6308},{"idEntity":5950392,"label":"appointment","extractorType":null,"nerdType":"http://nerd.eurecom.fr/ontology#Thing","uri":"http://dbpedia.org/resource/Appointment_of_Catholic_bishops","confidence":3.54342E-4,"relevance":0.5,"extractor":"nerdml","startChar":6349,"endChar":6360},{"idEntity":5950393,"label":"Salafists","extractorType":null,"nerdType":"http://nerd.eurecom.fr/ontology#Thing","uri":"http://dbpedia.org/resource/Salafi_movement","confidence":0.6898,"relevance":0.5,"extractor":"nerdml","startChar":6490,"endChar":6499},{"idEntity":5950394,"label":"new Egypt","extractorType":null,"nerdType":"http://nerd.eurecom.fr/ontology#Location","uri":"http://dbpedia.org/resource/New_Egypt,_New_Jersey","confidence":0.6762,"relevance":0.5,"extractor":"nerdml","startChar":6543,"endChar":6552},{"idEntity":5950395,"label":"Patrick","extractorType":null,"nerdType":"http://nerd.eurecom.fr/ontology#Thing","uri":"http://dbpedia.org/resource/Saint_Patrick","confidence":0.0105301,"relevance":0.5,"extractor":"nerdml","startChar":6554,"endChar":6561},{"idEntity":5950396,"label":"charter","extractorType":null,"nerdType":"http://nerd.eurecom.fr/ontology#Thing","uri":"http://dbpedia.org/resource/Charter","confidence":0.01293,"relevance":0.5,"extractor":"nerdml","startChar":6574,"endChar":6581},{"idEntity":5950397,"label":"plans","extractorType":null,"nerdType":"http://nerd.eurecom.fr/ontology#Thing","uri":"http://dbpedia.org/resource/Plan","confidence":0.00632359,"relevance":0.5,"extractor":"nerdml","startChar":6594,"endChar":6599},{"idEntity":5950398,"label":"constitution","extractorType":null,"nerdType":"http://nerd.eurecom.fr/ontology#Thing","uri":"http://dbpedia.org/resource/Constitution","confidence":0.6743,"relevance":0.5,"extractor":"nerdml","startChar":6643,"endChar":6655},{"idEntity":5950399,"label":"human rights","extractorType":null,"nerdType":"http://nerd.eurecom.fr/ontology#Thing","uri":"http://dbpedia.org/resource/Human_rights","confidence":0.7108,"relevance":0.5,"extractor":"nerdml","startChar":6668,"endChar":6680},{"idEntity":5950400,"label":"Salafists","extractorType":null,"nerdType":"http://nerd.eurecom.fr/ontology#Thing","uri":"http://dbpedia.org/resource/Salafi_movement","confidence":0.7134,"relevance":0.5,"extractor":"nerdml","startChar":6708,"endChar":6717},{"idEntity":5950401,"label":"constitution","extractorType":null,"nerdType":"http://nerd.eurecom.fr/ontology#Thing","uri":"http://dbpedia.org/resource/Constitution","confidence":0.050026,"relevance":0.5,"extractor":"nerdml","startChar":6775,"endChar":6787},{"idEntity":5950402,"label":"building","extractorType":null,"nerdType":"http://nerd.eurecom.fr/ontology#Thing","uri":"http://dbpedia.org/resource/Building","confidence":0.00757922,"relevance":0.5,"extractor":"nerdml","startChar":6788,"endChar":6796},{"idEntity":5950403,"label":"democracy","extractorType":null,"nerdType":"http://nerd.eurecom.fr/ontology#Thing","uri":"http://dbpedia.org/resource/Democracy","confidence":0.256151,"relevance":0.5,"extractor":"nerdml","startChar":6805,"endChar":6814},{"idEntity":5950404,"label":"campaign","extractorType":null,"nerdType":"http://nerd.eurecom.fr/ontology#Event","uri":"http://dbpedia.org/resource/Hundred_Days","confidence":0.0283867,"relevance":0.5,"extractor":"nerdml","startChar":6815,"endChar":6823},{"idEntity":5950405,"label":"International Idea","extractorType":null,"nerdType":"http://nerd.eurecom.fr/ontology#Thing","uri":"http://dbpedia.org/resource/International_Institute_for_Democracy_and_Electoral_Assistance","confidence":0.7438,"relevance":0.5,"extractor":"nerdml","startChar":6824,"endChar":6842},{"idEntity":5950406,"label":"tweets","extractorType":null,"nerdType":"http://nerd.eurecom.fr/ontology#Organization","uri":"http://dbpedia.org/resource/Twitter","confidence":0.0539126,"relevance":0.5,"extractor":"nerdml","startChar":6878,"endChar":6884},{"idEntity":5950407,"label":"Middle East","extractorType":null,"nerdType":"http://nerd.eurecom.fr/ontology#Thing","uri":"http://dbpedia.org/resource/Middle_East","confidence":0.768,"relevance":0.5,"extractor":"nerdml","startChar":6897,"endChar":6908},{"idEntity":5950408,"label":"Egyptian army","extractorType":null,"nerdType":"http://nerd.eurecom.fr/ontology#Thing","uri":"http://dbpedia.org/resource/Egyptian_Armed_Forces","confidence":0.7652,"relevance":0.5,"extractor":"nerdml","startChar":6919,"endChar":6932},{"idEntity":5950409,"label":"investigation","extractorType":null,"nerdType":"http://nerd.eurecom.fr/ontology#Thing","uri":"http://dbpedia.org/resource/Federal_Bureau_of_Investigation","confidence":0.0326714,"relevance":0.5,"extractor":"nerdml","startChar":6956,"endChar":6969},{"idEntity":5950410,"label":"president","extractorType":null,"nerdType":"http://nerd.eurecom.fr/ontology#Thing","uri":"http://dbpedia.org/resource/President_of_Egypt","confidence":0.675,"relevance":0.5,"extractor":"nerdml","startChar":7033,"endChar":7042},{"idEntity":5950411,"label":"Mohamed Morsi","extractorType":null,"nerdType":"http://nerd.eurecom.fr/ontology#Person","uri":"http://dbpedia.org/resource/Mohamed_Morsi","confidence":0.905,"relevance":0.5,"extractor":"nerdml","startChar":7043,"endChar":7056},{"idEntity":5950412,"label":"roundup","extractorType":null,"nerdType":"http://nerd.eurecom.fr/ontology#Thing","uri":"http://dbpedia.org/resource/Roundup_%28herbicide%29","confidence":0.00204579,"relevance":0.5,"extractor":"nerdml","startChar":7068,"endChar":7075},{"idEntity":5950413,"label":"Interim","extractorType":null,"nerdType":"http://nerd.eurecom.fr/ontology#Thing","uri":"http://dbpedia.org/resource/Interim","confidence":0.0135049,"relevance":0.5,"extractor":"nerdml","startChar":7106,"endChar":7113},{"idEntity":5950414,"label":"Adly Mansour","extractorType":null,"nerdType":"http://nerd.eurecom.fr/ontology#Thing","uri":"http://dbpedia.org/resource/Adly_Mansour","confidence":0.9134,"relevance":0.5,"extractor":"nerdml","startChar":7124,"endChar":7136},{"idEntity":5950415,"label":"constitution","extractorType":null,"nerdType":"http://nerd.eurecom.fr/ontology#Thing","uri":"http://dbpedia.org/resource/Constitution","confidence":0.7104,"relevance":0.5,"extractor":"nerdml","startChar":7178,"endChar":7190},{"idEntity":5950416,"label":"parliamentary","extractorType":null,"nerdType":"http://nerd.eurecom.fr/ontology#Thing","uri":"http://dbpedia.org/resource/Parliamentary_system","confidence":0.6712,"relevance":0.5,"extractor":"nerdml","startChar":7200,"endChar":7213},{"idEntity":5950417,"label":"presidential elections","extractorType":null,"nerdType":"http://nerd.eurecom.fr/ontology#Function","uri":"http://dbpedia.org/resource/Egyptian_presidential_election,_2012","confidence":0.6903,"relevance":0.5,"extractor":"nerdml","startChar":7218,"endChar":7240},{"idEntity":5950418,"label":"bloodiest day","extractorType":null,"nerdType":"http://nerd.eurecom.fr/ontology#Event","uri":"http://dbpedia.org/resource/Battle_of_Antietam","confidence":0.0166262,"relevance":0.5,"extractor":"nerdml","startChar":7267,"endChar":7280},{"idEntity":5950419,"label":"Egypt","extractorType":null,"nerdType":"http://nerd.eurecom.fr/ontology#Location","uri":"http://dbpedia.org/resource/Egypt","confidence":0.8476,"relevance":0.5,"extractor":"nerdml","startChar":7284,"endChar":7289},{"idEntity":5950420,"label":"Mohamed Morsi","extractorType":null,"nerdType":"http://nerd.eurecom.fr/ontology#Person","uri":"http://dbpedia.org/resource/Mohamed_Morsi","confidence":0.912,"relevance":0.5,"extractor":"nerdml","startChar":7360,"endChar":7373},{"idEntity":5950421,"label":"security forces","extractorType":null,"nerdType":"http://nerd.eurecom.fr/ontology#Thing","uri":"http://dbpedia.org/resource/Police","confidence":0.0296239,"relevance":0.5,"extractor":"nerdml","startChar":7389,"endChar":7404},{"idEntity":5950422,"label":"Muslim Brotherhood","extractorType":null,"nerdType":"http://nerd.eurecom.fr/ontology#Organization","uri":"http://dbpedia.org/resource/Muslim_Brotherhood","confidence":1.81468,"relevance":0.5,"extractor":"nerdml","startChar":7417,"endChar":7435},{"idEntity":5950423,"label":"condemned","extractorType":null,"nerdType":"http://nerd.eurecom.fr/ontology#Thing","uri":"http://dbpedia.org/resource/Capital_punishment","confidence":0.6446,"relevance":0.5,"extractor":"nerdml","startChar":7436,"endChar":7445},{"idEntity":5950424,"label":"massacre","extractorType":null,"nerdType":"http://nerd.eurecom.fr/ontology#Thing","uri":"http://dbpedia.org/resource/Massacre","confidence":0.6808,"relevance":0.5,"extractor":"nerdml","startChar":7451,"endChar":7459},{"idEntity":5950425,"label":"military","extractorType":null,"nerdType":"http://nerd.eurecom.fr/ontology#Thing","uri":"http://dbpedia.org/resource/Military","confidence":0.6529,"relevance":0.5,"extractor":"nerdml","startChar":7469,"endChar":7477},{"idEntity":5950426,"label":"Cairo","extractorType":null,"nerdType":"http://nerd.eurecom.fr/ontology#Location","uri":"http://dbpedia.org/resource/Cairo","confidence":0.8352,"relevance":0.5,"extractor":"nerdml","startChar":7526,"endChar":7531},{"idEntity":5950427,"label":"barracks","extractorType":null,"nerdType":"http://nerd.eurecom.fr/ontology#Thing","uri":"http://dbpedia.org/resource/Barracks","confidence":0.0209571,"relevance":0.5,"extractor":"nerdml","startChar":7532,"endChar":7540},{"idEntity":5950428,"label":"Egyptian army","extractorType":null,"nerdType":"http://nerd.eurecom.fr/ontology#Thing","uri":"http://dbpedia.org/resource/Egyptian_Army","confidence":0.79,"relevance":0.5,"extractor":"nerdml","startChar":7548,"endChar":7561},{"idEntity":5950429,"label":"excessive force","extractorType":null,"nerdType":"http://nerd.eurecom.fr/ontology#Thing","uri":"http://dbpedia.org/resource/Police_brutality","confidence":0.6718,"relevance":0.5,"extractor":"nerdml","startChar":7590,"endChar":7605},{"idEntity":5950430,"label":"Morsi","extractorType":null,"nerdType":"http://nerd.eurecom.fr/ontology#Person","uri":"http://dbpedia.org/resource/Mohamed_Morsi","confidence":0.6714,"relevance":0.5,"extractor":"nerdml","startChar":7618,"endChar":7623},{"idEntity":5950431,"label":"independent","extractorType":null,"nerdType":"http://nerd.eurecom.fr/ontology#Product","uri":"http://dbpedia.org/resource/The_Independent","confidence":0.6654,"relevance":0.5,"extractor":"nerdml","startChar":7653,"endChar":7664},{"idEntity":5950432,"label":"massacre","extractorType":null,"nerdType":"http://nerd.eurecom.fr/ontology#Thing","uri":"http://dbpedia.org/resource/Massacre","confidence":0.0522125,"relevance":0.5,"extractor":"nerdml","startChar":7696,"endChar":7704},{"idEntity":5950433,"label":"AP","extractorType":null,"nerdType":"http://nerd.eurecom.fr/ontology#Thing","uri":"http://dbpedia.org/resource/Associated_Press","confidence":0.631,"relevance":0.5,"extractor":"nerdml","startChar":7718,"endChar":7720},{"idEntity":5950434,"label":"spokesman","extractorType":null,"nerdType":"http://nerd.eurecom.fr/ontology#Thing","uri":"http://dbpedia.org/resource/Spokesperson","confidence":0.0142937,"relevance":0.5,"extractor":"nerdml","startChar":7722,"endChar":7731},{"idEntity":5950435,"label":"Colonel","extractorType":null,"nerdType":"http://nerd.eurecom.fr/ontology#Thing","uri":"http://dbpedia.org/resource/Colonel","confidence":0.6878,"relevance":0.5,"extractor":"nerdml","startChar":7732,"endChar":7739},{"idEntity":5950436,"label":"Ahmed Mohammed Ali","extractorType":null,"nerdType":"http://nerd.eurecom.fr/ontology#Thing","uri":"http://dbpedia.org/resource/Ahmed_Mohammed_Ali","confidence":0.7715,"relevance":0.5,"extractor":"nerdml","startChar":7740,"endChar":7758},{"idEntity":5950437,"label":"excessive force","extractorType":null,"nerdType":"http://nerd.eurecom.fr/ontology#Thing","uri":"http://dbpedia.org/resource/Police_brutality","confidence":0.6558,"relevance":0.5,"extractor":"nerdml","startChar":7770,"endChar":7785},{"idEntity":5950438,"label":"live ammunition","extractorType":null,"nerdType":"http://nerd.eurecom.fr/ontology#Product","uri":"http://dbpedia.org/resource/Ammunition","confidence":0.0234846,"relevance":0.5,"extractor":"nerdml","startChar":7835,"endChar":7850},{"idEntity":5950439,"label":"Amnesty","extractorType":null,"nerdType":"http://nerd.eurecom.fr/ontology#Organization","uri":"http://dbpedia.org/resource/Amnesty_International","confidence":0.6352,"relevance":0.5,"extractor":"nerdml","startChar":7899,"endChar":7906},{"idEntity":5950440,"label":"inquiry","extractorType":null,"nerdType":"http://nerd.eurecom.fr/ontology#Thing","uri":"http://dbpedia.org/resource/Inquiry","confidence":0.012519,"relevance":0.5,"extractor":"nerdml","startChar":7921,"endChar":7928},{"idEntity":5950441,"label":"white-washing","extractorType":null,"nerdType":"http://nerd.eurecom.fr/ontology#Thing","uri":"http://dbpedia.org/resource/Whitewash","confidence":0.6354,"relevance":0.5,"extractor":"nerdml","startChar":7959,"endChar":7972},{"idEntity":5950442,"label":"abuses","extractorType":null,"nerdType":"http://nerd.eurecom.fr/ontology#Thing","uri":"http://dbpedia.org/resource/Abuse","confidence":0.0136118,"relevance":0.5,"extractor":"nerdml","startChar":7973,"endChar":7979},{"idEntity":5950443,"label":"Egyptian army","extractorType":null,"nerdType":"http://nerd.eurecom.fr/ontology#Thing","uri":"http://dbpedia.org/resource/Egyptian_Army","confidence":0.7234,"relevance":0.5,"extractor":"nerdml","startChar":7987,"endChar":8000},{"idEntity":5950444,"label":"finance minister","extractorType":null,"nerdType":"http://nerd.eurecom.fr/ontology#Thing","uri":"http://dbpedia.org/resource/Finance_minister","confidence":0.0255619,"relevance":0.5,"extractor":"nerdml","startChar":8011,"endChar":8027},{"idEntity":5950445,"label":"Samir Radwan","extractorType":null,"nerdType":"http://nerd.eurecom.fr/ontology#Person","uri":"http://dbpedia.org/resource/Samir_Radwan","confidence":0.869,"relevance":0.5,"extractor":"nerdml","startChar":8028,"endChar":8040},{"idEntity":5950446,"label":"Egypt","extractorType":null,"nerdType":"http://nerd.eurecom.fr/ontology#Thing","uri":"http://dbpedia.org/resource/Egypt","confidence":0.429476,"relevance":0.5,"extractor":"nerdml","startChar":8084,"endChar":8089},{"idEntity":5950447,"label":"prime minister","extractorType":null,"nerdType":"http://nerd.eurecom.fr/ontology#Thing","uri":"http://dbpedia.org/resource/Prime_minister","confidence":0.7296,"relevance":0.5,"extractor":"nerdml","startChar":8100,"endChar":8114},{"idEntity":5950448,"label":"Reuters","extractorType":null,"nerdType":"http://nerd.eurecom.fr/ontology#Thing","uri":"http://dbpedia.org/resource/Reuters","confidence":0.8188,"relevance":0.5,"extractor":"nerdml","startChar":8116,"endChar":8123},{"idEntity":5950449,"label":"Salafist","extractorType":null,"nerdType":"http://nerd.eurecom.fr/ontology#Thing","uri":"http://dbpedia.org/resource/Salafi_movement","confidence":0.8178,"relevance":0.5,"extractor":"nerdml","startChar":8169,"endChar":8177},{"idEntity":5950450,"label":"al-Nour party","extractorType":null,"nerdType":"http://nerd.eurecom.fr/ontology#Organization","uri":"http://dbpedia.org/resource/Al-Nour_Party","confidence":0.8963,"relevance":0.5,"extractor":"nerdml","startChar":8178,"endChar":8191},{"idEntity":5950451,"label":"coup","extractorType":null,"nerdType":"http://nerd.eurecom.fr/ontology#Thing","uri":"http://dbpedia.org/resource/Coup_d'%C3%A9tat","confidence":0.6731,"relevance":0.5,"extractor":"nerdml","startChar":8218,"endChar":8222},{"idEntity":5950452,"label":"Muslim Brotherhood","extractorType":null,"nerdType":"http://nerd.eurecom.fr/ontology#Organization","uri":"http://dbpedia.org/resource/Muslim_Brotherhood","confidence":1.81468,"relevance":0.5,"extractor":"nerdml","startChar":8235,"endChar":8253},{"idEntity":5950453,"label":"liberal","extractorType":null,"nerdType":"http://nerd.eurecom.fr/ontology#Thing","uri":"http://dbpedia.org/resource/Liberalism","confidence":0.783,"relevance":0.5,"extractor":"nerdml","startChar":8282,"endChar":8289},{"idEntity":5950454,"label":"opposition leader","extractorType":null,"nerdType":"http://nerd.eurecom.fr/ontology#Thing","uri":"http://dbpedia.org/resource/Leader_of_the_Opposition","confidence":0.00806141,"relevance":0.5,"extractor":"nerdml","startChar":8290,"endChar":8307},{"idEntity":5950455,"label":"Mohammed ElBaradei","extractorType":null,"nerdType":"http://nerd.eurecom.fr/ontology#Person","uri":"http://dbpedia.org/resource/Mohamed_ElBaradei","confidence":0.8586,"relevance":0.5,"extractor":"nerdml","startChar":8308,"endChar":8326},{"idEntity":5950456,"label":"prime minister","extractorType":null,"nerdType":"http://nerd.eurecom.fr/ontology#Thing","uri":"http://dbpedia.org/resource/Prime_minister","confidence":0.7518,"relevance":0.5,"extractor":"nerdml","startChar":8330,"endChar":8344},{"idEntity":5950457,"label":"Protests","extractorType":null,"nerdType":"http://nerd.eurecom.fr/ontology#Thing","uri":"http://dbpedia.org/resource/Protest","confidence":0.6756,"relevance":0.5,"extractor":"nerdml","startChar":8349,"endChar":8357},{"idEntity":5950458,"label":"military","extractorType":null,"nerdType":"http://nerd.eurecom.fr/ontology#Thing","uri":"http://dbpedia.org/resource/Military","confidence":0.6504,"relevance":0.5,"extractor":"nerdml","startChar":8370,"endChar":8378},{"idEntity":5950459,"label":"Morsi","extractorType":null,"nerdType":"http://nerd.eurecom.fr/ontology#Person","uri":"http://dbpedia.org/resource/Mohamed_Morsi","confidence":0.915647,"relevance":0.5,"extractor":"nerdml","startChar":8399,"endChar":8404},{"idEntity":5950460,"label":"presidency","extractorType":null,"nerdType":"http://nerd.eurecom.fr/ontology#Thing","uri":"http://dbpedia.org/resource/Presidency_of_the_Council_of_the_European_Union","confidence":0.0319013,"relevance":0.5,"extractor":"nerdml","startChar":8424,"endChar":8434},{"idEntity":5950461,"label":"government","extractorType":null,"nerdType":"http://nerd.eurecom.fr/ontology#Thing","uri":"http://dbpedia.org/resource/Government","confidence":0.6473,"relevance":0.5,"extractor":"nerdml","startChar":8474,"endChar":8484},{"idEntity":5950462,"label":"the Guardian","extractorType":null,"nerdType":"http://nerd.eurecom.fr/ontology#Product","uri":"http://dbpedia.org/resource/The_Guardian","confidence":0.7935,"relevance":0.5,"extractor":"nerdml","startChar":8507,"endChar":8519},{"idEntity":5950463,"label":"attack","extractorType":null,"nerdType":"http://nerd.eurecom.fr/ontology#Thing","uri":"http://dbpedia.org/resource/September_11_attacks","confidence":0.0367269,"relevance":0.5,"extractor":"nerdml","startChar":8583,"endChar":8589},{"idEntity":5950464,"label":"democracy","extractorType":null,"nerdType":"http://nerd.eurecom.fr/ontology#Thing","uri":"http://dbpedia.org/resource/Democracy","confidence":0.7002,"relevance":0.5,"extractor":"nerdml","startChar":8593,"endChar":8602},{"idEntity":5950465,"label":"army","extractorType":null,"nerdType":"http://nerd.eurecom.fr/ontology#Organization","uri":"http://dbpedia.org/resource/French_Army","confidence":0.0460489,"relevance":0.5,"extractor":"nerdml","startChar":8688,"endChar":8692},{"idEntity":5950466,"label":"intervention","extractorType":null,"nerdType":"http://nerd.eurecom.fr/ontology#Location","uri":"http://dbpedia.org/resource/Economic_interventionism","confidence":0.6393,"relevance":0.5,"extractor":"nerdml","startChar":8724,"endChar":8736},{"idEntity":5950467,"label":"Egypt","extractorType":null,"nerdType":"http://nerd.eurecom.fr/ontology#Location","uri":"http://dbpedia.org/resource/Egypt","confidence":0.8308,"relevance":0.5,"extractor":"nerdml","startChar":8740,"endChar":8745},{"idEntity":5950468,"label":"politics","extractorType":null,"nerdType":"http://nerd.eurecom.fr/ontology#Thing","uri":"http://dbpedia.org/resource/Politics","confidence":0.6573,"relevance":0.5,"extractor":"nerdml","startChar":8748,"endChar":8756},{"idEntity":5950469,"label":"Egyptians","extractorType":null,"nerdType":"http://nerd.eurecom.fr/ontology#Location","uri":"http://dbpedia.org/resource/Ancient_Egypt","confidence":0.7145,"relevance":0.5,"extractor":"nerdml","startChar":8758,"endChar":8767},{"idEntity":5950470,"label":"right","extractorType":null,"nerdType":"http://nerd.eurecom.fr/ontology#Thing","uri":"http://dbpedia.org/resource/Rights","confidence":0.6721,"relevance":0.5,"extractor":"nerdml","startChar":8777,"endChar":8782},{"idEntity":5950471,"label":"suppressed","extractorType":null,"nerdType":"http://nerd.eurecom.fr/ontology#Thing","uri":"http://dbpedia.org/resource/Censorship","confidence":0.6558,"relevance":0.5,"extractor":"nerdml","startChar":8834,"endChar":8844},{"idEntity":5950472,"label":"democracy","extractorType":null,"nerdType":"http://nerd.eurecom.fr/ontology#Thing","uri":"http://dbpedia.org/resource/Democracy","confidence":0.7202,"relevance":0.5,"extractor":"nerdml","startChar":8857,"endChar":8866},{"idEntity":5950473,"label":"coup","extractorType":null,"nerdType":"http://nerd.eurecom.fr/ontology#Thing","uri":"http://dbpedia.org/resource/Coup_d'%C3%A9tat","confidence":0.6159,"relevance":0.5,"extractor":"nerdml","startChar":8907,"endChar":8911},{"idEntity":5950474,"label":"massacre","extractorType":null,"nerdType":"http://nerd.eurecom.fr/ontology#Thing","uri":"http://dbpedia.org/resource/Massacre","confidence":0.0799649,"relevance":0.5,"extractor":"nerdml","startChar":8921,"endChar":8929},{"idEntity":5950475,"label":"Obama administration","extractorType":null,"nerdType":"http://nerd.eurecom.fr/ontology#Person","uri":"http://dbpedia.org/resource/Barack_Obama","confidence":0.7613,"relevance":0.5,"extractor":"nerdml","startChar":8964,"endChar":8984},{"idEntity":5950476,"label":"military aid","extractorType":null,"nerdType":"http://nerd.eurecom.fr/ontology#Thing","uri":"http://dbpedia.org/resource/Military_aid","confidence":0.0574168,"relevance":0.5,"extractor":"nerdml","startChar":9038,"endChar":9050},{"idEntity":5950477,"label":"Egypt","extractorType":null,"nerdType":"http://nerd.eurecom.fr/ontology#Location","uri":"http://dbpedia.org/resource/Egypt","confidence":0.8219,"relevance":0.5,"extractor":"nerdml","startChar":9054,"endChar":9059},{"idEntity":5950478,"label":"Egypt","extractorType":null,"nerdType":"http://nerd.eurecom.fr/ontology#Location","uri":"http://dbpedia.org/resource/Egypt","confidence":0.823,"relevance":0.5,"extractor":"nerdml","startChar":9117,"endChar":9122},{"idEntity":5950479,"label":"events","extractorType":null,"nerdType":"http://nerd.eurecom.fr/ontology#Thing","uri":"http://dbpedia.org/resource/2004","confidence":0.0282902,"relevance":0.5,"extractor":"nerdml","startChar":9169,"endChar":9175},{"idEntity":5950480,"label":"military coup","extractorType":null,"nerdType":"http://nerd.eurecom.fr/ontology#Thing","uri":"http://dbpedia.org/resource/Coup_d'%C3%A9tat","confidence":0.6555,"relevance":0.5,"extractor":"nerdml","startChar":9190,"endChar":9203},{"idEntity":5950481,"label":"Spokesman","extractorType":null,"nerdType":"http://nerd.eurecom.fr/ontology#Thing","uri":"http://dbpedia.org/resource/Spokesperson","confidence":0.0142937,"relevance":0.5,"extractor":"nerdml","startChar":9205,"endChar":9214},{"idEntity":5950482,"label":"Jay Carney","extractorType":null,"nerdType":"http://nerd.eurecom.fr/ontology#Person","uri":"http://dbpedia.org/resource/Jay_Carney","confidence":0.8703,"relevance":0.5,"extractor":"nerdml","startChar":9215,"endChar":9225},{"idEntity":5950483,"label":"Egypt","extractorType":null,"nerdType":"http://nerd.eurecom.fr/ontology#Location","uri":"http://dbpedia.org/resource/Egypt","confidence":0.8253,"relevance":0.5,"extractor":"nerdml","startChar":9270,"endChar":9275},{"idEntity":5950484,"label":"Egyptian people","extractorType":null,"nerdType":"http://nerd.eurecom.fr/ontology#Thing","uri":"http://dbpedia.org/resource/Egyptians","confidence":0.0700165,"relevance":0.5,"extractor":"nerdml","startChar":9284,"endChar":9299},{"idEntity":5950485,"label":"wise","extractorType":null,"nerdType":"http://nerd.eurecom.fr/ontology#Thing","uri":"http://dbpedia.org/resource/Wisdom","confidence":0.6304,"relevance":0.5,"extractor":"nerdml","startChar":9320,"endChar":9324},{"idEntity":5950486,"label":"assistance","extractorType":null,"nerdType":"http://nerd.eurecom.fr/ontology#Product","uri":"http://dbpedia.org/resource/Assistance_dog","confidence":2.95285E-4,"relevance":0.5,"extractor":"nerdml","startChar":9348,"endChar":9358},{"idEntity":5950487,"label":"smart","extractorType":null,"nerdType":"http://nerd.eurecom.fr/ontology#Thing","uri":"http://dbpedia.org/resource/Intelligence","confidence":0.6887,"relevance":0.5,"extractor":"nerdml","startChar":9374,"endChar":9379},{"idEntity":5950488,"label":"policy","extractorType":null,"nerdType":"http://nerd.eurecom.fr/ontology#Thing","uri":"http://dbpedia.org/resource/Policy","confidence":0.644,"relevance":0.5,"extractor":"nerdml","startChar":9380,"endChar":9386},{"idEntity":5950489,"label":"matter","extractorType":null,"nerdType":"http://nerd.eurecom.fr/ontology#Product","uri":"http://dbpedia.org/resource/Matter","confidence":0.00358092,"relevance":0.5,"extractor":"nerdml","startChar":9405,"endChar":9411},{"idEntity":5950490,"label":"argument","extractorType":null,"nerdType":"http://nerd.eurecom.fr/ontology#Thing","uri":"http://dbpedia.org/resource/Argument","confidence":0.6667,"relevance":0.5,"extractor":"nerdml","startChar":9417,"endChar":9425},{"idEntity":5950491,"label":"army","extractorType":null,"nerdType":"http://nerd.eurecom.fr/ontology#Organization","uri":"http://dbpedia.org/resource/French_Army","confidence":0.0460489,"relevance":0.5,"extractor":"nerdml","startChar":9435,"endChar":9439},{"idEntity":5950492,"label":"coup","extractorType":null,"nerdType":"http://nerd.eurecom.fr/ontology#Thing","uri":"http://dbpedia.org/resource/Coup_d%27%C3%A9tat","confidence":0.0698838,"relevance":0.5,"extractor":"nerdml","startChar":9489,"endChar":9493},{"idEntity":5950493,"label":"security forces","extractorType":null,"nerdType":"http://nerd.eurecom.fr/ontology#Thing","uri":"http://dbpedia.org/resource/Police","confidence":0.0296239,"relevance":0.5,"extractor":"nerdml","startChar":9552,"endChar":9567},{"idEntity":5950494,"label":"disorder","extractorType":null,"nerdType":"http://nerd.eurecom.fr/ontology#Thing","uri":"http://dbpedia.org/resource/Disease","confidence":0.0164425,"relevance":0.5,"extractor":"nerdml","startChar":9597,"endChar":9605},{"idEntity":5950495,"label":"violence","extractorType":null,"nerdType":"http://nerd.eurecom.fr/ontology#Thing","uri":"http://dbpedia.org/resource/Violence","confidence":0.0254289,"relevance":0.5,"extractor":"nerdml","startChar":9610,"endChar":9618},{"idEntity":5950496,"label":"army","extractorType":null,"nerdType":"http://nerd.eurecom.fr/ontology#Organization","uri":"http://dbpedia.org/resource/French_Army","confidence":0.0460489,"relevance":0.5,"extractor":"nerdml","startChar":9624,"endChar":9628},{"idEntity":5950497,"label":"orange juice","extractorType":null,"nerdType":"http://nerd.eurecom.fr/ontology#Thing","uri":"http://dbpedia.org/resource/Orange_juice","confidence":0.7382,"relevance":0.5,"extractor":"nerdml","startChar":9670,"endChar":9682},{"idEntity":5950498,"label":"side","extractorType":null,"nerdType":"http://nerd.eurecom.fr/ontology#Thing","uri":"http://dbpedia.org/resource/Side","confidence":0.00872615,"relevance":0.5,"extractor":"nerdml","startChar":9705,"endChar":9709},{"idEntity":5950499,"label":"bullets","extractorType":null,"nerdType":"http://nerd.eurecom.fr/ontology#Thing","uri":"http://dbpedia.org/resource/Bullet","confidence":0.0189445,"relevance":0.5,"extractor":"nerdml","startChar":9721,"endChar":9728},{"idEntity":5950500,"label":"army","extractorType":null,"nerdType":"http://nerd.eurecom.fr/ontology#Organization","uri":"http://dbpedia.org/resource/French_Army","confidence":0.0460489,"relevance":0.5,"extractor":"nerdml","startChar":9750,"endChar":9754},{"idEntity":5950501,"label":"protector","extractorType":null,"nerdType":"http://nerd.eurecom.fr/ontology#Thing","uri":"http://dbpedia.org/resource/Lord_Protector","confidence":0.0172034,"relevance":0.5,"extractor":"nerdml","startChar":9769,"endChar":9778},{"idEntity":5950502,"label":"Egyptians","extractorType":null,"nerdType":"http://nerd.eurecom.fr/ontology#Location","uri":"http://dbpedia.org/resource/Ancient_Egypt","confidence":0.6757,"relevance":0.5,"extractor":"nerdml","startChar":9786,"endChar":9795},{"idEntity":5950503,"label":"eyes","extractorType":null,"nerdType":"http://nerd.eurecom.fr/ontology#Thing","uri":"http://dbpedia.org/resource/Eye","confidence":0.0025844,"relevance":0.5,"extractor":"nerdml","startChar":9825,"endChar":9829}]