[{"label":"Sierra Leone","type":"         GPE","link":"http://dbpedia.org/resource/Sierra_Leone","score":0.4327826086956525,"provenance":"Expansion"},{"label":"Koroma","type":"         PER","link":"http://dbpedia.org/resource/Ernest_Bai_Koroma","score":0.2918260869565217,"provenance":"Expansion"},{"label":"Samuel Sam-Sumana","type":"         GPE","link":"http://dbpedia.org/resource/American_Samoa","score":0.24234782608695646,"provenance":"Expansion"},{"label":"Guinea","type":"         GPE","link":"http://dbpedia.org/resource/Guinea","score":0.19721739130434784,"provenance":"Expansion"},{"label":"Ministry of Health","type":"         ORG","link":"http://dbpedia.org/resource/World_Health_Organization","score":0.13617391304347823,"provenance":"Expansion"},{"label":"CDC","type":"         ORG","link":"http://dbpedia.org/resource/Centers_for_Disease_Control_and_Prevention","score":0.12208695652173912,"provenance":"Expansion"},{"label":"Liberia","type":"         GPE","link":"http://dbpedia.org/resource/Liberia","score":0.10973913043478259,"provenance":"Expansion"},{"label":"Freetown","type":"         GPE","link":"http://dbpedia.org/resource/Freetown","score":0.10086956521739128,"provenance":"Expansion"},{"label":"European Union","type":"         GPE","link":"http://dbpedia.org/resource/European_Union","score":0.041913043478260865,"provenance":"Expansion"},{"label":"Nicol","type":"         PER","link":"http://dbpedia.org/resource/Nicol_Williamson","score":0.03286956521739131,"provenance":"Expansion"},{"label":"Mr Sam","type":"         PER","link":"http://dbpedia.org/resource/Mr._Sam","score":0.03721739130434783,"provenance":"Expansion"},{"label":"Belgium","type":"         GPE","link":"http://dbpedia.org/resource/Belgium","score":0.03147826086956521,"provenance":"Expansion"},{"label":"Haiti","type":"         GPE","link":"http://dbpedia.org/resource/Haiti","score":0.025826086956521742,"provenance":"Expansion"},{"label":"British military","type":"         GPE","link":"http://dbpedia.org/resource/British_Armed_Forces","score":0.02426086956521739,"provenance":"Expansion"},{"label":"Metropolitan State University","type":"         ORG","link":"http://dbpedia.org/resource/Metropolitan_State_University","score":0.021130434782608697,"provenance":"Expansion"},{"label":"African nations","type":"         GPE","link":"http://dbpedia.org/resource/Africa","score":0.02104347826086957,"provenance":"Expansion"},{"label":"China","type":"         GPE","link":"http://dbpedia.org/resource/China","score":0.016869565217391302,"provenance":"Expansion"},{"label":"UK","type":"         GPE","link":"http://dbpedia.org/resource/United_Kingdom","score":0.016434782608695655,"provenance":"Expansion"},{"label":"Centre for Health Protection","type":"         ORG","link":"http://dbpedia.org/resource/Centre_for_Health_Protection","score":0.01408695652173913,"provenance":"Expansion"},{"label":"Brussels","type":"         GPE","link":"http://dbpedia.org/resource/Brussels","score":0.01173913043478261,"provenance":"Expansion"},{"label":"Canada","type":"         GPE","link":"http://dbpedia.org/resource/Canada","score":0.01173913043478261,"provenance":"Expansion"},{"label":"William Randolph Hearst","type":"         PER","link":"http://dbpedia.org/resource/William_Randolph_Hearst","score":0.01165217391304348,"provenance":"Expansion"},{"label":"Rybicki","type":"         PER","link":"http://dbpedia.org/resource/Jerzy_Rybicki","score":0.009391304347826087,"provenance":"Expansion"},{"label":"John A. Carroll","type":"         PER","link":"http://dbpedia.org/resource/John_A._Carroll","score":0.009391304347826087,"provenance":"Expansion"},{"label":"Clarke","type":"         PER","link":"http://dbpedia.org/resource/Arthur_C._Clarke","score":0.009391304347826087,"provenance":"Expansion"},{"label":"Brasil","type":"         GPE","link":"http://dbpedia.org/resource/Brazil","score":0.008695652173913044,"provenance":"Expansion"},{"label":"Fuller House","type":"         GPE","link":"http://dbpedia.org/resource/Fuller_House_(Washington,_D.C.)","score":0.008434782608695653,"provenance":"Expansion"},{"label":"Asa Hutchinson","type":"         PER","link":"http://dbpedia.org/resource/Asa_Hutchinson","score":0.00817391304347826,"provenance":"Expansion"},{"label":"Senators","type":"         ORG","link":"http://dbpedia.org/resource/United_States_Senate","score":0.008086956521739132,"provenance":"Expansion"},{"label":"Indiana","type":"         GPE","link":"http://dbpedia.org/resource/Indiana","score":0.008,"provenance":"Expansion,Editor"},{"label":"Mali","type":"         GPE","link":"http://dbpedia.org/resource/Mali","score":0.007391304347826088,"provenance":"Expansion,Editor"},{"label":"Samuel Sam-Sumana","type":"         PER","link":"http://en.wikipedia.org/wiki/Samuel_Sam-Sumana","score":0.0,"provenance":"Banner,Editor"},{"label":"Sierra Leone","type":"         GPE","link":"http://en.wikipedia.org/wiki/Sierra_Leone","score":0.0,"provenance":"Banner,Editor"}]